{
  "dev": {
    "awscloudformation": {
      "AuthRoleName": "amplify-newapp-dev-233618-authRole",
      "UnauthRoleArn": "arn:aws:iam::319163603467:role/amplify-newapp-dev-233618-unauthRole",
      "AuthRoleArn": "arn:aws:iam::319163603467:role/amplify-newapp-dev-233618-authRole",
      "Region": "us-west-1",
      "DeploymentBucketName": "amplify-newapp-dev-233618-deployment",
      "UnauthRoleName": "amplify-newapp-dev-233618-unauthRole",
      "StackName": "amplify-newapp-dev-233618",
      "StackId": "arn:aws:cloudformation:us-west-1:319163603467:stack/amplify-newapp-dev-233618/2b22fdd0-7c77-11ee-aab4-063b6394062b",
      "AmplifyAppId": "d3mxfxvj02tj0v",
      "APIGatewayAuthURL": "https://s3.amazonaws.com/amplify-newapp-dev-233618-deployment/amplify-cfn-templates/api/APIGatewayAuthStack.json"
    },
    "categories": {
      "auth": {
        "newapp": {}
      },
      "function": {
        "handleDeleteResumeProfile": {},
        "handleGetResumeProfile": {},
        "handleRegisterUser": {},
        "handleResumeUploadEvent": {},
        "handleStoringScrapedJobs": {},
        "handleUpdateResumeProfile": {},
        "handleUserLogin": {},
        "handleUserSaveJobListing": {},
        "handleUserUnsaveJobListing": {},
        "handleUserUpdate": {},
        "handleUserViewSavedJobListings": {},
        "newapp732e55b5": {},
        "queryGoogleJobs": {},
        "scrapeJobListings": {}
      },
      "hosting": {
        "amplifyhosting": {
          "appId": "d3mxfxvj02tj0v",
          "type": "manual"
        }
      }
    }
  }
}